{
  "title": "Nimona",
  "description": "Nimona is an impulsive young shape-shifter with a knack for villainy. Lord Ballister Blackheart is a villain with a vendetta. As sidekick and supervillain, Nimona and Lord Blackheart are about to wreak some serious havoc. Their mission: prove to the kingdom that Sir Ambrosius Goldenloin and his buddies at the Institution of Law Enforcement and Heroics aren’t the heroes everyone thinks they are. But as small acts of mischief escalate into a vicious battle, Lord Blackheart realizes that Nimona’s powers are as murky and mysterious as her past. And her unpredictable wild side might be more dangerous than he is willing to admit.",
  "artist": "Noelle Stevenson",
  "author": "Noelle Stevenson",
  "cover": "https://i.gr-assets.com/images/S/compressed.photo.goodreads.com/books/1412626919l/19351043._SX0_SY0_.jpg",
  "chapters": {
    "1": {
      "title": "Nimona",
      "volume": "",
      "last_updated": "1668982991",
      "groups": {
        "": ""
      }
    }
  }
}