{
  "title": "V For Vendetta",
  "description": "Set in a futuristic totalitarian England, a country without political freedom, personal freedom, and precious little faith in anything, a mysterious man in a white porcelain mask fights political oppressors through terrorism and seemingly absurd acts. It’s a gripping tale of the blurred lines between ideological good and evil.",
  "artist": "David Lloyd",
  "author": "Alan Moore",
  "cover": "https://tommygirard.files.wordpress.com/2020/08/v-for-vendetta-cover.jpg",
  "chapters": {
    "1": {
      "title": "V For Vendetta",
      "volume": "",
      "last_updated": "1668987682",
      "groups": {
        "": ""
      }
    }
  }
}